LICENSE
MANIFEST.in
README.rst
setup.py
simple_daemon/__init__.py
simple_daemon.egg-info/PKG-INFO
simple_daemon.egg-info/SOURCES.txt
simple_daemon.egg-info/dependency_links.txt
simple_daemon.egg-info/requires.txt
simple_daemon.egg-info/top_level.txt