Metadata-Version: 1.0
Name: simple-daemon
Version: 0.0.4
Summary: Simple nix daemon
Home-page: https://bitbucket.org/imbolc/simple_daemon
Author: Imbolc
Author-email: imbolc@imbolc.name
License: ISC
Platform: UNKNOWN
Classifier: Development Status :: 4 - Beta
Classifier: Intended Audience :: Developers
Classifier: Natural Language :: English
Classifier: License :: OSI Approved :: ISC License (ISCL)
Classifier: Programming Language :: Python
